LICENSE
README.md
setup.py
beamshapes/__init__.py
beamshapes/beamshape_predictions.py
beamshapes/cap_in_sphere.py
beamshapes/compare_predictions_to_data.py
beamshapes/flint_parallelisation.py
beamshapes/piston_in_infinite_baffle.py
beamshapes/piston_in_sphere.py
beamshapes/piston_in_sphere_flint.py
beamshapes/point_source_on_a_sphere.py
beamshapes/sim_reclevels.py
beamshapes/special_functions.py
beamshapes/utilities.py
beamshapes/version.py
beamshapes.egg-info/PKG-INFO
beamshapes.egg-info/SOURCES.txt
beamshapes.egg-info/dependency_links.txt
beamshapes.egg-info/not-zip-safe
beamshapes.egg-info/requires.txt
beamshapes.egg-info/top_level.txt
beamshapes/tests/__init__.py
beamshapes/tests/test_osccapsphere.py
beamshapes/tests/test_pistoninfbaffle.py
beamshapes/tests/test_pistoninsphere_mpmath.py
beamshapes/tests/test_pistoninsphereflint.py
beamshapes/tests/test_pointsourcesphere.py