Metadata-Version: 2.1
Name: beamshapes
Version: 0.2.1
Summary: Acoustic beamshape modelling for various sources
Home-page: https://github.com/thejasvibr/bat_beamshapes.git
Author: Thejasvi Beleyur
Author-email: thejasvib@gmail.com
License: MIT
Platform: UNKNOWN
Classifier: Intended Audience :: Science/Research
Classifier: Topic :: Multimedia :: Sound/Audio :: Analysis
Classifier: Programming Language :: Python :: 3
